modelgauge/annotators/openai_compliance_annotator.py
modelgauge/suts/openai_client.py
modelgauge_openai-0.6.3.dist-info/METADATA
modelgauge_openai-0.6.3.dist-info/WHEEL
modelgauge_openai-0.6.3.dist-info/RECORD
