Metadata-Version: 2.1
Name: modelgauge-openai
Version: 0.6.3
Summary: 
Author: MLCommons AI Safety
Author-email: ai-safety-engineering@mlcommons.org
Requires-Python: >=3.10,<4.0
Classifier: Programming Language :: Python :: 3
Classifier: Programming Language :: Python :: 3.10
Classifier: Programming Language :: Python :: 3.11
Classifier: Programming Language :: Python :: 3.12
Requires-Dist: openai (>=1.8.0,<2.0.0)
